mobio_media_sdk-0.2.8-py3.8-nspkg.pth
mobio/sdks/media/__init__.py
mobio/sdks/media/config.py
mobio/sdks/media/constant.py
mobio/sdks/media/custom_mimetypes.py
mobio/sdks/media/dir.py
mobio/sdks/media/merchant_config.py
mobio/sdks/media/mobio_media_sdk.py
mobio/sdks/media/utils.py
mobio_media_sdk-0.2.8.dist-info/LICENSE
mobio_media_sdk-0.2.8.dist-info/METADATA
mobio_media_sdk-0.2.8.dist-info/WHEEL
mobio_media_sdk-0.2.8.dist-info/namespace_packages.txt
mobio_media_sdk-0.2.8.dist-info/top_level.txt
mobio_media_sdk-0.2.8.dist-info/RECORD
