Metadata-Version: 2.1
Name: mobio-media-sdk
Version: 0.2.8
Summary: Mobio media SDK
Home-page: https://github.com/mobiovn
Author: MOBIO
Author-email: contact@mobio.vn
License: MIT
Project-URL: Source, https://github.com/mobiovn
Keywords: mobio,media,file
Classifier: Development Status :: 3 - Alpha
Classifier: Intended Audience :: Developers
Classifier: Topic :: Software Development :: Build Tools
Classifier: License :: OSI Approved :: MIT License
Classifier: Programming Language :: Python :: 3
Classifier: Programming Language :: Python :: 3.6
Classifier: Programming Language :: Python :: 3.7
Classifier: Programming Language :: Python :: 3.8
Classifier: Programming Language :: Python :: 3.9
Classifier: Programming Language :: Python :: 3 :: Only
Requires-Python: >=3
License-File: LICENSE
Requires-Dist: Werkzeug
Requires-Dist: Flask
Requires-Dist: m-caching
Requires-Dist: m-singleton
Requires-Dist: requests
Requires-Dist: confluent-kafka (==1.5.0)
Requires-Dist: python-magic
Requires-Dist: mobio-admin-sdk
